Metadata-Version: 2.1
Name: cp-mn-bd-01-mimicat
Version: 0.0.2
Summary: (C) CNSIDE (P) Payload - (M) Malicious (N) Non Harmful - (B) Binary (D) Dormant -  01 - Mimikatz
Home-page: https://illustria.io
Author: Bogdan Kortnov
Author-email: bogdan@illustria.io
License: MIT
Platform: UNKNOWN
License-File: LICENSE.txt
